{
 "country": {
  "cc": "DE",
  "name": "Germany",
  "ll": [
   10,
   51
  ],
  "deployments": 40,
  "companies": 40,
  "searched": 40,
  "confirmed": 39,
  "confirmed_pct": 98,
  "density": 0.97,
  "with_value_number": 8,
  "proof_pct": 20,
  "top_verticals": [
   {
    "v": "Retail & E-commerce",
    "n": 6
   },
   {
    "v": "Healthcare & Life Sciences",
    "n": 6
   },
   {
    "v": "Automotive",
    "n": 6
   },
   {
    "v": "Financial Services",
    "n": 4
   },
   {
    "v": "Aerospace & Defence",
    "n": 3
   }
  ]
 },
 "grid": [
  {
   "v": "Financial Services",
   "h": "Core / Domain",
   "n": 1,
   "withnum": 1,
   "verdict": "strong",
   "verdict_v2": "proven"
  },
  {
   "v": "Financial Services",
   "h": "Sales / Marketing",
   "n": 1,
   "withnum": 0,
   "verdict": "talk",
   "verdict_v2": "unquantified"
  },
  {
   "v": "Financial Services",
   "h": "Back-office / Ops",
   "n": 2,
   "withnum": 2,
   "verdict": "strong",
   "verdict_v2": "proven"
  },
  {
   "v": "Retail & E-commerce",
   "h": "Core / Domain",
   "n": 2,
   "withnum": 1,
   "verdict": "strong",
   "verdict_v2": "proven"
  },
  {
   "v": "Retail & E-commerce",
   "h": "Customer Support",
   "n": 3,
   "withnum": 2,
   "verdict": "strong",
   "verdict_v2": "proven"
  },
  {
   "v": "Retail & E-commerce",
   "h": "Sales / Marketing",
   "n": 1,
   "withnum": 0,
   "verdict": "talk",
   "verdict_v2": "unquantified"
  },
  {
   "v": "Energy & Utilities",
   "h": "Core / Domain",
   "n": 2,
   "withnum": 0,
   "verdict": "talk",
   "verdict_v2": "unquantified"
  },
  {
   "v": "Energy & Utilities",
   "h": "Back-office / Ops",
   "n": 1,
   "withnum": 0,
   "verdict": "talk",
   "verdict_v2": "unquantified"
  },
  {
   "v": "Industrial / Machinery",
   "h": "Core / Domain",
   "n": 2,
   "withnum": 0,
   "verdict": "talk",
   "verdict_v2": "unquantified"
  },
  {
   "v": "Healthcare & Life Sciences",
   "h": "Core / Domain",
   "n": 5,
   "withnum": 1,
   "verdict": "active",
   "verdict_v2": "active"
  },
  {
   "v": "Healthcare & Life Sciences",
   "h": "Back-office / Ops",
   "n": 1,
   "withnum": 0,
   "verdict": "talk",
   "verdict_v2": "unquantified"
  },
  {
   "v": "Technology",
   "h": "Core / Domain",
   "n": 1,
   "withnum": 0,
   "verdict": "talk",
   "verdict_v2": "unquantified"
  },
  {
   "v": "Technology",
   "h": "Software / Code",
   "n": 1,
   "withnum": 0,
   "verdict": "talk",
   "verdict_v2": "unquantified"
  },
  {
   "v": "Real Estate & Construction",
   "h": "Core / Domain",
   "n": 1,
   "withnum": 0,
   "verdict": "talk",
   "verdict_v2": "talk"
  },
  {
   "v": "Chemicals & Materials",
   "h": "Core / Domain",
   "n": 2,
   "withnum": 0,
   "verdict": "talk",
   "verdict_v2": "unquantified"
  },
  {
   "v": "Chemicals & Materials",
   "h": "Back-office / Ops",
   "n": 1,
   "withnum": 0,
   "verdict": "talk",
   "verdict_v2": "unquantified"
  },
  {
   "v": "Telecom",
   "h": "Customer Support",
   "n": 1,
   "withnum": 0,
   "verdict": "talk",
   "verdict_v2": "unquantified"
  },
  {
   "v": "Insurance",
   "h": "Core / Domain",
   "n": 1,
   "withnum": 0,
   "verdict": "talk",
   "verdict_v2": "unquantified"
  },
  {
   "v": "Insurance",
   "h": "Security / Risk",
   "n": 1,
   "withnum": 0,
   "verdict": "talk",
   "verdict_v2": "unquantified"
  },
  {
   "v": "Logistics & Supply Chain",
   "h": "Customer Support",
   "n": 1,
   "withnum": 0,
   "verdict": "talk",
   "verdict_v2": "unquantified"
  },
  {
   "v": "Automotive",
   "h": "Core / Domain",
   "n": 4,
   "withnum": 0,
   "verdict": "talk",
   "verdict_v2": "unquantified"
  },
  {
   "v": "Automotive",
   "h": "Software / Code",
   "n": 2,
   "withnum": 1,
   "verdict": "strong",
   "verdict_v2": "proven"
  },
  {
   "v": "Aerospace & Defence",
   "h": "Core / Domain",
   "n": 3,
   "withnum": 0,
   "verdict": "talk",
   "verdict_v2": "unquantified"
  }
 ],
 "verticals": [
  {
   "v": "Retail & E-commerce",
   "n": 6,
   "confirmed": 6,
   "withnum": 3,
   "proof_pct": 50,
   "verdict": "strong",
   "verdict_v2": "proven"
  },
  {
   "v": "Healthcare & Life Sciences",
   "n": 6,
   "confirmed": 6,
   "withnum": 1,
   "proof_pct": 17,
   "verdict": "active",
   "verdict_v2": "active"
  },
  {
   "v": "Automotive",
   "n": 6,
   "confirmed": 6,
   "withnum": 1,
   "proof_pct": 17,
   "verdict": "active",
   "verdict_v2": "active"
  },
  {
   "v": "Financial Services",
   "n": 4,
   "confirmed": 4,
   "withnum": 3,
   "proof_pct": 75,
   "verdict": "strong",
   "verdict_v2": "proven"
  },
  {
   "v": "Energy & Utilities",
   "n": 3,
   "confirmed": 3,
   "withnum": 0,
   "proof_pct": 0,
   "verdict": "talk",
   "verdict_v2": "unquantified"
  },
  {
   "v": "Chemicals & Materials",
   "n": 3,
   "confirmed": 3,
   "withnum": 0,
   "proof_pct": 0,
   "verdict": "talk",
   "verdict_v2": "unquantified"
  },
  {
   "v": "Aerospace & Defence",
   "n": 3,
   "confirmed": 3,
   "withnum": 0,
   "proof_pct": 0,
   "verdict": "talk",
   "verdict_v2": "unquantified"
  },
  {
   "v": "Industrial / Machinery",
   "n": 2,
   "confirmed": 2,
   "withnum": 0,
   "proof_pct": 0,
   "verdict": "talk",
   "verdict_v2": "unquantified"
  },
  {
   "v": "Technology",
   "n": 2,
   "confirmed": 2,
   "withnum": 0,
   "proof_pct": 0,
   "verdict": "talk",
   "verdict_v2": "unquantified"
  },
  {
   "v": "Insurance",
   "n": 2,
   "confirmed": 2,
   "withnum": 0,
   "proof_pct": 0,
   "verdict": "talk",
   "verdict_v2": "unquantified"
  },
  {
   "v": "Real Estate & Construction",
   "n": 1,
   "confirmed": 0,
   "withnum": 0,
   "proof_pct": 0,
   "verdict": "talk",
   "verdict_v2": "talk"
  },
  {
   "v": "Telecom",
   "n": 1,
   "confirmed": 1,
   "withnum": 0,
   "proof_pct": 0,
   "verdict": "talk",
   "verdict_v2": "unquantified"
  },
  {
   "v": "Logistics & Supply Chain",
   "n": 1,
   "confirmed": 1,
   "withnum": 0,
   "proof_pct": 0,
   "verdict": "talk",
   "verdict_v2": "unquantified"
  }
 ]
}