{
 "slug": "air-france-klm",
 "name": "Air France-KLM",
 "cc": "FR",
 "vertical": "Travel & Hospitality",
 "deployments": 1,
 "confirmed": 1,
 "with_value_number": 0,
 "proof_rate": 0.0,
 "mktcap": 3294000000.0,
 "revenue": 35985600000.0,
 "employees": 79755.0,
 "silent": false,
 "per_bn_revenue": 0.03,
 "per_10k_emp": 0.13,
 "benchmarks": {
  "global_vertical": {
   "deployments": 0,
   "confirmed": 29,
   "proof_rate": 0,
   "n": 39
  },
  "country_vertical": {
   "deployments": 0,
   "confirmed": 0,
   "proof_rate": 0,
   "n": 6
  }
 },
 "first_seen": 2025,
 "by_year": [
  {
   "year": 2025,
   "n": 1
  }
 ],
 "undated_pct": 0,
 "momentum": "rising",
 "maturity": "L3",
 "maturity_evidence": [
  "named_product:Gen",
  "tier_p"
 ],
 "prospect_score": 54,
 "stack": [],
 "vendor_named": false,
 "deployments_detail": [
  {
   "company": "Air France-KLM",
   "use": "Gen AI Factory built with Google Cloud and Accenture to industrialize generative AI across operations",
   "existence": "confirmed",
   "value": "none",
   "tier": "P",
   "url": "https://corporate.airfrance.com/fr/actualites/air-france-et-lintelligence-artificielle-ia",
   "raw_sector": "Airlines",
   "date": "2025",
   "fresh": "fresh"
  }
 ]
}