{
 "slug": "almarai",
 "name": "Almarai",
 "cc": "SA",
 "vertical": "Retail & E-commerce",
 "deployments": 2,
 "confirmed": 1,
 "with_value_number": 0,
 "proof_rate": 0.0,
 "mktcap": 12288000000.0,
 "revenue": 6144000000.0,
 "employees": 46997.0,
 "silent": false,
 "per_bn_revenue": 0.33,
 "per_10k_emp": 0.43,
 "benchmarks": {
  "global_vertical": {
   "deployments": 78,
   "confirmed": 26,
   "proof_rate": 0,
   "n": 273
  }
 },
 "first_seen": 2024,
 "by_year": [
  {
   "year": 2024,
   "n": 2
  }
 ],
 "undated_pct": 0,
 "momentum": "early_mover,gone_quiet",
 "maturity": "L3",
 "maturity_evidence": [
  "named_product:Technology",
  "tier_p"
 ],
 "prospect_score": 46,
 "stack": [
  "Google Cloud"
 ],
 "vendor_named": true,
 "deployments_detail": [
  {
   "company": "Almarai",
   "use": "AI and machine learning applied across marketing, supply chain, HR and finance functions (company Technology & Innovation disclosure / annual report)",
   "existence": "confirmed",
   "value": "none",
   "tier": "P",
   "url": "https://almarai.lava-brands.com/assets/img/pdfs/Technology%20and%20Innovation.pdf",
   "raw_sector": "Food",
   "date": "2024",
   "fresh": "aging"
  },
  {
   "company": "Almarai",
   "use": "Migration to Google Cloud with Business Intelligence Center using AI to improve productivity and operational efficiency",
   "existence": "claimed",
   "value": "none",
   "tier": "I",
   "url": "https://www.datacenterdynamics.com/en/news/saudi-dairy-company-almarai-migrates-to-google-cloud/",
   "raw_sector": "Food",
   "date": "2024",
   "fresh": "aging"
  }
 ]
}