{
 "slug": "aneka-tambang",
 "name": "Aneka Tambang",
 "cc": "ID",
 "vertical": "Mining & Materials",
 "deployments": 1,
 "confirmed": 1,
 "with_value_number": 0,
 "proof_rate": 0.0,
 "mktcap": 4685443038.0,
 "revenue": 5356962025.0,
 "employees": 3829.0,
 "silent": false,
 "per_bn_revenue": 0.19,
 "per_10k_emp": 2.61,
 "benchmarks": {
  "global_vertical": {
   "deployments": 0,
   "confirmed": 38,
   "proof_rate": 0,
   "n": 61
  },
  "country_vertical": {
   "deployments": 0,
   "confirmed": 62,
   "proof_rate": 0,
   "n": 9
  }
 },
 "first_seen": 2026,
 "by_year": [
  {
   "year": 2026,
   "n": 1
  }
 ],
 "undated_pct": 0,
 "momentum": "late_entrant,rising",
 "maturity": "L3",
 "maturity_evidence": [
  "named_product:Geologging"
 ],
 "prospect_score": 54,
 "stack": [],
 "vendor_named": false,
 "deployments_detail": [
  {
   "company": "Aneka Tambang",
   "use": "'Geologging' AI/machine-learning digital data-capturing app initiated by Antam for gold/mineral exploration (calculates RQD, core recovery from drill core samples), part of MIND ID smart-mining program",
   "existence": "confirmed",
   "value": "none",
   "tier": "I",
   "url": "https://www.marketeers.com/antam-perkuat-efisiensi-eksplorasi-dan-operasional-pertambangan-lewat-ai/",
   "raw_sector": "Mining",
   "date": "2026",
   "fresh": "fresh"
  }
 ]
}