{
 "slug": "cintas",
 "name": "Cintas",
 "cc": "US",
 "vertical": "Industrial / Machinery",
 "deployments": 1,
 "confirmed": 0,
 "with_value_number": 1,
 "proof_rate": 1.0,
 "mktcap": null,
 "revenue": null,
 "employees": null,
 "silent": false,
 "benchmarks": {
  "global_vertical": {
   "deployments": 0,
   "confirmed": 0,
   "proof_rate": 78,
   "n": 175
  },
  "country_vertical": {
   "deployments": 0,
   "confirmed": 0,
   "proof_rate": 89,
   "n": 80
  }
 },
 "first_seen": null,
 "by_year": [],
 "undated_pct": 100,
 "momentum": "none",
 "maturity": "L1",
 "maturity_evidence": [
  "rows_no_confirmed"
 ],
 "prospect_score": 0,
 "stack": [
  "SAP"
 ],
 "vendor_named": true,
 "deployments_detail": [
  {
   "company": "Cintas",
   "use": "AI-driven scheduling/dispatching w/ SAP + AI coding assistants (target 30% of code) — 3rd-party sourced, no primary announcement",
   "existence": "claimed",
   "value": "~30% of code via AI (target)",
   "tier": "S",
   "url": "https://infotechlead.com/digital/cintas-says-ai-and-digital-transformation-drive-revenue-growth-margin-efficiency-and-customer-retention-92799",
   "raw_sector": "Industrials",
   "date": "missing",
   "fresh": "undated"
  }
 ]
}