{
 "slug": "ck-asset-holdings",
 "name": "CK Asset Holdings",
 "cc": "HK",
 "vertical": "Real Estate & Construction",
 "deployments": 1,
 "confirmed": 0,
 "with_value_number": 0,
 "proof_rate": 0.0,
 "mktcap": 21680769231.0,
 "revenue": 7428205128.0,
 "employees": 54000.0,
 "silent": false,
 "per_bn_revenue": 0.13,
 "per_10k_emp": 0.19,
 "benchmarks": {
  "global_vertical": {
   "deployments": 0,
   "confirmed": 0,
   "proof_rate": 0,
   "n": 154
  },
  "country_vertical": {
   "deployments": 0,
   "confirmed": 0,
   "proof_rate": 0,
   "n": 8
  }
 },
 "first_seen": 2026,
 "by_year": [
  {
   "year": 2026,
   "n": 1
  }
 ],
 "undated_pct": 0,
 "momentum": "late_entrant,rising",
 "maturity": "L1",
 "maturity_evidence": [
  "rows_no_confirmed"
 ],
 "prospect_score": 40,
 "stack": [],
 "vendor_named": false,
 "deployments_detail": [
  {
   "company": "CK Asset Holdings",
   "use": "AI-driven energy management systems and tenant experience platforms across portfolio; largest institutional shareholder in NEXX Global robotics-driven warehouse/logistics AI firm",
   "existence": "claimed",
   "value": "none",
   "tier": "I",
   "url": "https://getproptechbrief.com",
   "raw_sector": "Real Estate",
   "date": "2026",
   "fresh": "fresh"
  }
 ]
}