{
 "slug": "coloplast",
 "name": "Coloplast",
 "cc": "DK",
 "vertical": "Healthcare & Life Sciences",
 "deployments": 2,
 "confirmed": 1,
 "with_value_number": 0,
 "proof_rate": 0.0,
 "mktcap": 13437681159.0,
 "revenue": 4065217391.0,
 "employees": 17083.0,
 "silent": false,
 "per_bn_revenue": 0.49,
 "per_10k_emp": 1.17,
 "benchmarks": {
  "global_vertical": {
   "deployments": 86,
   "confirmed": 14,
   "proof_rate": 0,
   "n": 149
  },
  "country_vertical": {
   "deployments": 71,
   "confirmed": 29,
   "proof_rate": 0,
   "n": 8
  }
 },
 "first_seen": null,
 "by_year": [],
 "undated_pct": 100,
 "momentum": "none",
 "maturity": "L2",
 "maturity_evidence": [
  "tier_p"
 ],
 "prospect_score": 54,
 "stack": [],
 "vendor_named": false,
 "deployments_detail": [
  {
   "company": "Coloplast",
   "use": "Edge AI in Heylo ostomy sensor providing predictive leakage/ostomy protection",
   "existence": "claimed",
   "value": "none",
   "tier": "I",
   "url": "https://northhavenanalytics.com/case-study-coloplast-heylo-ai-intelligence-layer/",
   "raw_sector": "Healthcare",
   "date": "missing",
   "fresh": "undated"
  },
  {
   "company": "Coloplast",
   "use": "Impact4 five-year strategy investing in AI to enhance customer centricity and operational efficiency",
   "existence": "confirmed",
   "value": "none",
   "tier": "P",
   "url": "https://www.biospace.com/press-releases/coloplast-a-s-coloplast-presents-new-5-year-strategy-impact4",
   "raw_sector": "Healthcare",
   "date": "missing",
   "fresh": "undated"
  }
 ]
}