{
 "slug": "cyrela",
 "name": "Cyrela",
 "cc": "BR",
 "vertical": "Real Estate & Construction",
 "deployments": 1,
 "confirmed": 1,
 "with_value_number": 0,
 "proof_rate": 0.0,
 "mktcap": 1701851852.0,
 "revenue": 1762962963.0,
 "employees": 984.0,
 "silent": false,
 "per_bn_revenue": 0.57,
 "per_10k_emp": 10.16,
 "benchmarks": {
  "global_vertical": {
   "deployments": 0,
   "confirmed": 34,
   "proof_rate": 0,
   "n": 156
  },
  "country_vertical": {
   "deployments": 0,
   "confirmed": 20,
   "proof_rate": 0,
   "n": 6
  }
 },
 "first_seen": null,
 "by_year": [],
 "undated_pct": 100,
 "momentum": "none",
 "maturity": "L3",
 "maturity_evidence": [
  "named_product:Cyrela"
 ],
 "prospect_score": 54,
 "stack": [],
 "vendor_named": false,
 "deployments_detail": [
  {
   "company": "Cyrela",
   "use": "AI concierge with five specialized generative-AI virtual agents handling cinema/events/store inquiries at a Cyrela retail-development spin-off",
   "existence": "confirmed",
   "value": "none",
   "tier": "I",
   "url": "https://exame.com/mercado-imobiliario/spin-off-da-cyrela-usa-ia-para-oferecer-experiencia-de-hotel-em-shopping-popular/",
   "raw_sector": "Consumo cíclico e construção civil",
   "date": "missing",
   "fresh": "undated"
  }
 ]
}