{
 "slug": "hanmi-semiconductor",
 "name": "Hanmi Semiconductor",
 "cc": "KR",
 "vertical": "Electric Machinery & Electronics",
 "deployments": 1,
 "confirmed": 1,
 "with_value_number": 0,
 "proof_rate": 0.0,
 "mktcap": 15177777778.0,
 "revenue": 427170370.0,
 "employees": 698.0,
 "silent": false,
 "per_bn_revenue": 2.34,
 "per_10k_emp": 14.33,
 "benchmarks": {
  "global_vertical": {
   "deployments": 0,
   "confirmed": 12,
   "proof_rate": 0,
   "n": 35
  }
 },
 "first_seen": 2025,
 "by_year": [
  {
   "year": 2025,
   "n": 1
  }
 ],
 "undated_pct": 0,
 "momentum": "early_mover,rising",
 "maturity": "L3",
 "maturity_evidence": [
  "named_product:Research",
  "tier_p"
 ],
 "prospect_score": 54,
 "stack": [],
 "vendor_named": false,
 "deployments_detail": [
  {
   "company": "Hanmi Semiconductor",
   "use": "AI Research Division (Sep 2025, ~150 staff); AI integrated into TC Bonder 4 for HBM4 (process optimization, predictive analytics)",
   "existence": "confirmed",
   "value": "NONE",
   "tier": "P",
   "url": "https://html.duckduckgo.com/html/?q=한미반도체+AI+제조+도입",
   "raw_sector": "IT",
   "date": "2025-09",
   "fresh": "fresh"
  }
 ]
}