{
 "slug": "imperial-oil",
 "name": "Imperial Oil",
 "cc": "CA",
 "vertical": "Energy & Utilities",
 "deployments": 1,
 "confirmed": 0,
 "with_value_number": 0,
 "proof_rate": 0.0,
 "mktcap": 62955882353.0,
 "revenue": 34463235294.0,
 "employees": 5000.0,
 "silent": false,
 "per_bn_revenue": 0.03,
 "per_10k_emp": 2.0,
 "benchmarks": {
  "global_vertical": {
   "deployments": 0,
   "confirmed": 0,
   "proof_rate": 0,
   "n": 184
  },
  "country_vertical": {
   "deployments": 0,
   "confirmed": 0,
   "proof_rate": 0,
   "n": 7
  }
 },
 "first_seen": 2025,
 "by_year": [
  {
   "year": 2025,
   "n": 1
  }
 ],
 "undated_pct": 0,
 "momentum": "rising",
 "maturity": "L1",
 "maturity_evidence": [
  "rows_no_confirmed"
 ],
 "prospect_score": 40,
 "stack": [],
 "vendor_named": false,
 "deployments_detail": [
  {
   "company": "Imperial Oil",
   "use": "Integrated robots, drones, autonomous haul trucks and generative AI into oil sands operations since 2018; Amii ML partnership",
   "existence": "claimed",
   "value": "none",
   "tier": "I",
   "url": "https://boereport.com/2025/05/11/take-it-to-the-next-level-oil-and-gas-industry-players-embracing-ai-and-other-tech/",
   "raw_sector": "Energy",
   "date": "2025-05",
   "fresh": "fresh"
  }
 ]
}