{
 "slug": "informa",
 "name": "Informa",
 "cc": "UK",
 "vertical": "Media / Entertainment / Gaming",
 "deployments": 1,
 "confirmed": 1,
 "with_value_number": 0,
 "proof_rate": 0.0,
 "mktcap": null,
 "revenue": null,
 "employees": null,
 "silent": false,
 "benchmarks": {
  "global_vertical": {
   "deployments": 0,
   "confirmed": 22,
   "proof_rate": 0,
   "n": 28
  }
 },
 "first_seen": null,
 "by_year": [],
 "undated_pct": 100,
 "momentum": "none",
 "maturity": "L3",
 "maturity_evidence": [
  "named_product:Microsoft"
 ],
 "prospect_score": 46,
 "deployments_detail": [
  {
   "company": "Informa",
   "use": "Microsoft AI deal to deepen AI use; CEO betting on AI for growth; Conference AI partnership to monetise event content year-round",
   "existence": "confirmed",
   "value": "none",
   "tier": "S",
   "url": "https://www.wsj.com/business/media/informa-ceo-bets-on-ai-to-accelerate-growth",
   "raw_sector": "Media",
   "date": "missing",
   "fresh": "undated"
  }
 ]
}