{
 "slug": "kimco-realty",
 "name": "Kimco Realty",
 "cc": "US",
 "vertical": "Real Estate & Construction",
 "deployments": 1,
 "confirmed": 0,
 "with_value_number": 0,
 "proof_rate": 0.0,
 "mktcap": null,
 "revenue": null,
 "employees": null,
 "silent": false,
 "benchmarks": {
  "global_vertical": {
   "deployments": 0,
   "confirmed": 0,
   "proof_rate": 0,
   "n": 134
  },
  "country_vertical": {
   "deployments": 0,
   "confirmed": 0,
   "proof_rate": 0,
   "n": 31
  }
 },
 "first_seen": null,
 "by_year": [],
 "undated_pct": 100,
 "momentum": "none",
 "maturity": "L1",
 "maturity_evidence": [
  "rows_no_confirmed"
 ],
 "prospect_score": 40,
 "stack": [],
 "vendor_named": false,
 "deployments_detail": [
  {
   "company": "Kimco Realty",
   "use": "AI for site selection/consumer behavior (conference discussion) + automated dynamic leasing pages — no clearly named production AI system",
   "existence": "claimed",
   "value": "none",
   "tier": "—",
   "url": "https://www.icsc.com/news-and-views/icsc-exchange/how-kimco-automated-leasing-and-boosted-deal-flow",
   "raw_sector": "Real Estate",
   "date": "missing",
   "fresh": "undated"
  }
 ]
}