{
 "slug": "mondi",
 "name": "Mondi",
 "cc": "ZA",
 "vertical": "Manufacturing & Robotics",
 "deployments": 1,
 "confirmed": 1,
 "with_value_number": 0,
 "proof_rate": 0.0,
 "mktcap": null,
 "revenue": null,
 "employees": null,
 "silent": false,
 "benchmarks": {
  "global_vertical": {
   "deployments": 0,
   "confirmed": 24,
   "proof_rate": 0,
   "n": 108
  }
 },
 "first_seen": null,
 "by_year": [],
 "undated_pct": 100,
 "momentum": "none",
 "maturity": "L3",
 "maturity_evidence": [
  "named_product:Machine",
  "tier_p"
 ],
 "prospect_score": 46,
 "deployments_detail": [
  {
   "company": "Mondi",
   "use": "Machine learning-based health monitoring and predictive maintenance for paper manufacturing processes (with MathWorks)",
   "existence": "confirmed",
   "value": "none",
   "tier": "P",
   "url": "https://www.mathworks.com/company/user_stories/mondi-implements-statistics-based-health-monitoring-and-predictive-maintenance-for-manufacturing-processes-with-machine-learning.html",
   "raw_sector": "Paper",
   "date": "missing",
   "fresh": "undated"
  }
 ]
}