{
 "slug": "perusahaan-gas-negara",
 "name": "Perusahaan Gas Negara",
 "cc": "ID",
 "vertical": "Energy & Utilities",
 "deployments": 1,
 "confirmed": 0,
 "with_value_number": 0,
 "proof_rate": 0.0,
 "mktcap": null,
 "revenue": null,
 "employees": null,
 "silent": false,
 "benchmarks": {
  "global_vertical": {
   "deployments": 0,
   "confirmed": 0,
   "proof_rate": 0,
   "n": 176
  }
 },
 "first_seen": 2024,
 "by_year": [
  {
   "year": 2024,
   "n": 1
  }
 ],
 "undated_pct": 0,
 "momentum": "early_mover,gone_quiet",
 "maturity": "L1",
 "maturity_evidence": [
  "rows_no_confirmed"
 ],
 "prospect_score": 40,
 "stack": [],
 "vendor_named": false,
 "deployments_detail": [
  {
   "company": "Perusahaan Gas Negara",
   "use": "IoT and AI-driven automation to reduce energy consumption and emissions; AI for gas-infrastructure development and distribution clustering (per CEO)",
   "existence": "claimed",
   "value": "none",
   "tier": "I",
   "url": "https://www.cnbcindonesia.com/news/20241223171506-4-598251/efisiensi-operasional-pgn-lakukan-inovasi-digitalisasi-terintegrasi",
   "raw_sector": "Energy",
   "date": "2024-12",
   "fresh": "aging"
  }
 ]
}