{
 "slug": "quest-diagnostics",
 "name": "Quest Diagnostics",
 "cc": "US",
 "vertical": "Healthcare & Life Sciences",
 "deployments": 1,
 "confirmed": 1,
 "with_value_number": 0,
 "proof_rate": 0.0,
 "mktcap": null,
 "revenue": null,
 "employees": null,
 "silent": false,
 "benchmarks": {
  "global_vertical": {
   "deployments": 0,
   "confirmed": 14,
   "proof_rate": 0,
   "n": 149
  },
  "country_vertical": {
   "deployments": 0,
   "confirmed": 7,
   "proof_rate": 0,
   "n": 59
  }
 },
 "first_seen": 2024,
 "by_year": [
  {
   "year": 2024,
   "n": 1
  }
 ],
 "undated_pct": 0,
 "momentum": "early_mover,gone_quiet",
 "maturity": "L3",
 "maturity_evidence": [
  "named_product:Acquired",
  "tier_p"
 ],
 "prospect_score": 46,
 "deployments_detail": [
  {
   "company": "Quest Diagnostics",
   "use": "Acquired PathAI Diagnostics (AI digital pathology for cancer diagnosis) + Google Cloud GenAI customer service",
   "existence": "confirmed",
   "value": "none",
   "tier": "P",
   "url": "https://newsroom.questdiagnostics.com/2024-05-01-Quest-Diagnostics-to-Acquire-PathAI-Diagnostics-to-Accelerate-AI-and-Digital-Pathology-Adoption-in-Cancer-Diagnosis-Forms-Licensing-Agreements-with-PathAI",
   "raw_sector": "Health Care",
   "date": "2024",
   "fresh": "aging"
  }
 ]
}