{
 "slug": "regency-centers",
 "name": "Regency Centers",
 "cc": "US",
 "vertical": "Real Estate & Construction",
 "deployments": 1,
 "confirmed": 0,
 "with_value_number": 0,
 "proof_rate": 0.0,
 "mktcap": 15180000000.0,
 "revenue": 1650000000.0,
 "employees": 507.0,
 "silent": false,
 "per_bn_revenue": 0.61,
 "per_10k_emp": 19.72,
 "benchmarks": {
  "global_vertical": {
   "deployments": 0,
   "confirmed": 0,
   "proof_rate": 0,
   "n": 134
  },
  "country_vertical": {
   "deployments": 0,
   "confirmed": 0,
   "proof_rate": 0,
   "n": 31
  }
 },
 "first_seen": null,
 "by_year": [],
 "undated_pct": 100,
 "momentum": "none",
 "maturity": "L1",
 "maturity_evidence": [
  "rows_no_confirmed"
 ],
 "prospect_score": 40,
 "stack": [],
 "vendor_named": false,
 "deployments_detail": [
  {
   "company": "Regency Centers",
   "use": "no confirmed own AI deployment found (only 3rd-party commentary)",
   "existence": "claimed",
   "value": "none",
   "tier": "—",
   "url": "https://www.regencycenters.com",
   "raw_sector": "Real Estate",
   "date": "missing",
   "fresh": "undated"
  }
 ]
}