{
 "slug": "sands-china-hk",
 "name": "Sands China",
 "cc": "HK",
 "vertical": "Media / Entertainment / Gaming",
 "deployments": 1,
 "confirmed": 0,
 "with_value_number": 1,
 "proof_rate": 1.0,
 "mktcap": 13696153846.0,
 "revenue": 7426923077.0,
 "employees": 27875.0,
 "silent": false,
 "per_bn_revenue": 0.13,
 "per_10k_emp": 0.36,
 "benchmarks": {
  "global_vertical": {
   "deployments": 0,
   "confirmed": 0,
   "proof_rate": 59,
   "n": 28
  }
 },
 "first_seen": 2025,
 "by_year": [
  {
   "year": 2025,
   "n": 1
  }
 ],
 "undated_pct": 0,
 "momentum": "early_mover,rising",
 "maturity": "L1",
 "maturity_evidence": [
  "rows_no_confirmed"
 ],
 "prospect_score": 0,
 "stack": [],
 "vendor_named": false,
 "deployments_detail": [
  {
   "company": "Sands China",
   "use": "Smart-table system on 1,100+ baccarat tables (AI + RFID chip capture, by Jan 2025); AI-driven patron-data \"new frontier\"; AI ops training",
   "existence": "confirmed",
   "value": "1,100+ smart tables (self-claimed)",
   "tier": "I",
   "url": "https://wizardofmacau.com/zh-Hant/news/angel-group-expands-smart-table-system-across-macau",
   "raw_sector": "Commerce & Industry (HSI)",
   "date": "2025-01",
   "fresh": "fresh"
  },
  {
   "company": "Sands China",
   "use": "AI + RFID smart-table system (Angel Group) capturing chip information and quantities across 1,100+ baccarat tables in Macau properties",
   "existence": "claimed",
   "value": "1,100+ tables deployed",
   "tier": "I",
   "url": "https://www.ggrasia.com/angels-smart-table-product-deployed-across-all-sands-chinas-properties-in-macau",
   "raw_sector": "Gaming",
   "date": "2025-01",
   "fresh": "fresh"
  }
 ]
}