{
 "slug": "uniqa-insurance-group",
 "name": "Uniqa Insurance Group",
 "cc": "AT",
 "vertical": "Insurance",
 "deployments": 2,
 "confirmed": 1,
 "with_value_number": 1,
 "proof_rate": 0.5,
 "mktcap": null,
 "revenue": null,
 "employees": null,
 "silent": false,
 "benchmarks": {
  "global_vertical": {
   "deployments": 54,
   "confirmed": 15,
   "proof_rate": 56,
   "n": 55
  }
 },
 "first_seen": null,
 "by_year": [],
 "undated_pct": 100,
 "momentum": "none",
 "maturity": "L3",
 "maturity_evidence": [
  "named_product:Claims",
  "tier_p"
 ],
 "prospect_score": 26,
 "deployments_detail": [
  {
   "company": "Uniqa Insurance Group",
   "use": "Claims processing runs almost fully automatically with AI; thousands of claims, health-insurance and legal-protection cases handled without human intervention, with AI services now offered to third-party clients",
   "existence": "confirmed",
   "value": "none",
   "tier": "P",
   "url": "https://press-news.uniqagroup.com/news-kuenstliche-intelligenz-bei-uniqa",
   "raw_sector": "Insurance",
   "date": "missing",
   "fresh": "undated"
  },
  {
   "company": "Uniqa Insurance Group",
   "use": "AI chatbot for insurance sales support (Zuehlke) achieving 50% reduced effort at 95% answer accuracy",
   "existence": "claimed",
   "value": "50% reduced effort, 95% answer accuracy",
   "tier": "I",
   "url": "https://www.zuehlke.com/de/case-studies/uniqa-effizienzsteigerung-durch-ki-chatbot",
   "raw_sector": "Insurance",
   "date": "missing",
   "fresh": "undated"
  }
 ]
}