{
 "slug": "xiaomi-cn",
 "name": "Xiaomi",
 "cc": "CN",
 "vertical": "Commerce & Industry",
 "deployments": 0,
 "confirmed": 0,
 "with_value_number": 0,
 "proof_rate": 0,
 "mktcap": 89556410256.0,
 "revenue": 64867948718.0,
 "employees": 55994.0,
 "silent": true,
 "index": "HSI",
 "per_bn_revenue": 0.0,
 "per_10k_emp": 0.0,
 "maturity": "L0",
 "maturity_evidence": [
  "silent"
 ],
 "prospect_score": 0,
 "stack": [],
 "deployments_detail": [
  {
   "company": "Xiaomi",
   "use": "MiMo self-developed large model deployed across the \"human-car-home\" ecosystem; MiMo-V2-Flash open-source version",
   "existence": "confirmed",
   "value": "1 trillion tokens processed",
   "tier": "P",
   "url": "https://www.sohu.com/a/1005418136_122066678",
   "raw_sector": "Technology",
   "date": "2025-12",
   "fresh": "fresh"
  },
  {
   "company": "Xiaomi",
   "use": "Super Xiao Ai (小爱同学) voice assistant upgraded with MiMo models for conversation, reasoning and device control",
   "existence": "confirmed",
   "value": "none",
   "tier": "P",
   "url": "https://post.smzdm.com/p/an56qqd2/",
   "raw_sector": "Technology",
   "date": "2025",
   "fresh": "fresh"
  }
 ]
}